<Ui xmlns="http://www.blizzard.com/wow/ui/">
  <Script file="Mail.lua" />
  <Script file="Posting.lua" />
  <Script file="Vendor.lua" />
  <Script file="CraftingOrderPlacing.lua" />
  <Script file="CraftingOrderFulfilling.lua" />
  <Script file="QuestsClassic.lua" />
  <Script file="QuestsMainline.lua" />
  <Script file="Reputation.lua" />
  <Script file="TradingPost.lua" />
  <Script file="LootContainers.lua" />
  <Script file="LootRightClickToOpen.lua" />
  <Script file="WoWTokens.lua" />

  <Include file="Mail.xml" />
  <Include file="Posting.xml" />
  <Include file="Vendor.xml" />
  <Include file="CraftingOrderPlacing.xml" />
  <Include file="CraftingOrderFulfilling.xml" />
  <Include file="QuestsClassic.xml" />
  <Include file="QuestsMainline.xml" />
  <Include file="Reputation.xml" />
  <Include file="TradingPost.xml" />
  <Include file="LootContainers.xml" />
  <Include file="LootRightClickToOpen.xml" />
  <Include file="WoWTokens.xml" />
</Ui>
